Metadata-Version: 2.1
Name: ezztui
Version: 1.0.0
Summary: Easy TextUI creating package
Home-page: https://github.com/BarsTiger/ezztui
Author: BarsTiger
License: MIT
Platform: UNKNOWN
License-File: LICENSE.txt
